{
  "generatedAt": "2026-07-22",
  "note": "The five strongest decks from the portfolio (3 Spark of Rebellion, 2 Ashes of the Empire), fit into five deck boxes at once — each kept as close as possible to its original build, with premium printings applied first.",
  "roster": [
    {
      "id": "travel-phoenix-ignition",
      "name": "Phoenix Ignition",
      "archetype": "Aggro · Go-wide Rebels",
      "identity": "This deck wins by flooding the board with cheap Rebels and letting Sabine's unavoidable base damage finish what coordinated attacks start, before big defenders stabilize.",
      "aspects": [
        "Aggression",
        "Heroism",
        "Command"
      ],
      "leader": {
        "id": "SOR-14",
        "printing": "SOR-280",
        "variant": "Hyperspace"
      },
      "base": {
        "id": "SOR-23",
        "printing": "SOR-289",
        "variant": "Hyperspace"
      },
      "cards": [
        {
          "id": "ASH-184",
          "count": 1,
          "printings": [
            {
              "key": "ASH-184",
              "variant": "Standard",
              "count": 1
            }
          ]
        },
        {
          "id": "SOR-168",
          "count": 3,
          "printings": [
            {
              "key": "SOR-168",
              "variant": "Standard Foil",
              "count": 1
            },
            {
              "key": "SOR-168",
              "variant": "Standard",
              "count": 2
            }
          ]
        },
        {
          "id": "SOR-169",
          "count": 1,
          "printings": [
            {
              "key": "SOR-432",
              "variant": "Hyperspace",
              "count": 1
            }
          ]
        },
        {
          "id": "ASH-164",
          "count": 1,
          "printings": [
            {
              "key": "ASH-164",
              "variant": "Standard",
              "count": 1
            }
          ]
        },
        {
          "id": "SOR-156",
          "count": 1,
          "printings": [
            {
              "key": "SOR-156",
              "variant": "Standard",
              "count": 1
            }
          ]
        },
        {
          "id": "ASH-152",
          "count": 1,
          "printings": [
            {
              "key": "ASH-152",
              "variant": "Standard",
              "count": 1
            }
          ]
        },
        {
          "id": "SOR-140",
          "count": 2,
          "printings": [
            {
              "key": "SOR-140",
              "variant": "Standard",
              "count": 2
            }
          ]
        },
        {
          "id": "SOR-108",
          "count": 3,
          "printings": [
            {
              "key": "SOR-108",
              "variant": "Standard Foil",
              "count": 1
            },
            {
              "key": "SOR-108",
              "variant": "Standard",
              "count": 2
            }
          ]
        },
        {
          "id": "SOR-237",
          "count": 3,
          "printings": [
            {
              "key": "SOR-237",
              "variant": "Standard",
              "count": 3
            }
          ]
        },
        {
          "id": "SOR-95",
          "count": 2,
          "printings": [
            {
              "key": "SOR-95",
              "variant": "Standard",
              "count": 2
            }
          ]
        },
        {
          "id": "ASH-119",
          "count": 2,
          "printings": [
            {
              "key": "ASH-383",
              "variant": "Hyperspace",
              "count": 1
            },
            {
              "key": "ASH-119",
              "variant": "Standard",
              "count": 1
            }
          ]
        },
        {
          "id": "SOR-141",
          "count": 1,
          "printings": [
            {
              "key": "SOR-141",
              "variant": "Standard",
              "count": 1
            }
          ]
        },
        {
          "id": "SOR-158",
          "count": 2,
          "printings": [
            {
              "key": "SOR-158",
              "variant": "Standard",
              "count": 2
            }
          ]
        },
        {
          "id": "SOR-239",
          "count": 3,
          "printings": [
            {
              "key": "SOR-239",
              "variant": "Standard",
              "count": 3
            }
          ]
        },
        {
          "id": "SOR-142",
          "count": 1,
          "printings": [
            {
              "key": "SOR-142",
              "variant": "Standard",
              "count": 1
            }
          ]
        },
        {
          "id": "ASH-120",
          "count": 1,
          "printings": [
            {
              "key": "ASH-120",
              "variant": "Standard",
              "count": 1
            }
          ]
        },
        {
          "id": "SOR-161",
          "count": 2,
          "printings": [
            {
              "key": "SOR-161",
              "variant": "Standard",
              "count": 2
            }
          ]
        },
        {
          "id": "SOR-98",
          "count": 2,
          "printings": [
            {
              "key": "SOR-362",
              "variant": "Hyperspace",
              "count": 1
            },
            {
              "key": "SOR-98",
              "variant": "Standard",
              "count": 1
            }
          ]
        },
        {
          "id": "SOR-143",
          "count": 1,
          "printings": [
            {
              "key": "SOR-143",
              "variant": "Standard",
              "count": 1
            }
          ]
        },
        {
          "id": "SOR-240",
          "count": 3,
          "printings": [
            {
              "key": "SOR-240",
              "variant": "Standard",
              "count": 3
            }
          ]
        },
        {
          "id": "SOR-113",
          "count": 2,
          "printings": [
            {
              "key": "SOR-377",
              "variant": "Hyperspace",
              "count": 1
            },
            {
              "key": "SOR-113",
              "variant": "Standard",
              "count": 1
            }
          ]
        },
        {
          "id": "ASH-123",
          "count": 1,
          "printings": [
            {
              "key": "ASH-123",
              "variant": "Standard",
              "count": 1
            }
          ]
        },
        {
          "id": "SOR-241",
          "count": 1,
          "printings": [
            {
              "key": "SOR-241",
              "variant": "Standard",
              "count": 1
            }
          ]
        },
        {
          "id": "SOR-242",
          "count": 1,
          "printings": [
            {
              "key": "SOR-242",
              "variant": "Standard",
              "count": 1
            }
          ]
        },
        {
          "id": "ASH-158",
          "count": 1,
          "printings": [
            {
              "key": "ASH-660",
              "variant": "Hyperspace Foil",
              "count": 1
            }
          ]
        },
        {
          "id": "SOR-243",
          "count": 1,
          "printings": [
            {
              "key": "SOR-243",
              "variant": "Standard",
              "count": 1
            }
          ]
        },
        {
          "id": "ASH-173",
          "count": 1,
          "printings": [
            {
              "key": "ASH-173",
              "variant": "Standard",
              "count": 1
            }
          ]
        },
        {
          "id": "SOR-164",
          "count": 3,
          "printings": [
            {
              "key": "SOR-164",
              "variant": "Standard Foil",
              "count": 1
            },
            {
              "key": "SOR-164",
              "variant": "Standard",
              "count": 2
            }
          ]
        },
        {
          "id": "ASH-130",
          "count": 1,
          "printings": [
            {
              "key": "ASH-632",
              "variant": "Hyperspace Foil",
              "count": 1
            }
          ]
        },
        {
          "id": "SOR-146",
          "count": 1,
          "printings": [
            {
              "key": "SOR-146",
              "variant": "Standard Foil",
              "count": 1
            }
          ]
        },
        {
          "id": "SOR-149",
          "count": 1,
          "printings": [
            {
              "key": "SOR-149",
              "variant": "Standard",
              "count": 1
            }
          ]
        }
      ]
    },
    {
      "id": "travel-bounty-compound-interest",
      "name": "Bounty Compound Interest",
      "archetype": "Midrange · Premium value",
      "identity": "This deck wins midrange fights by converting every enemy unit that leaves play into an extra resource through Boba's leader ability, then banking that tempo into premium threats the opponent must answer.",
      "aspects": [
        "Cunning",
        "Villainy",
        "Command"
      ],
      "leader": {
        "id": "SOR-15",
        "printing": "SOR-281",
        "variant": "Hyperspace"
      },
      "base": {
        "id": "SOR-23",
        "printing": "SOR-23",
        "variant": "Standard"
      },
      "cards": [
        {
          "id": "SOR-217",
          "count": 3,
          "printings": [
            {
              "key": "SOR-217",
              "variant": "Standard",
              "count": 3
            }
          ]
        },
        {
          "id": "SOR-186",
          "count": 2,
          "printings": [
            {
              "key": "SOR-449",
              "variant": "Hyperspace Foil",
              "count": 1
            },
            {
              "key": "SOR-186",
              "variant": "Standard",
              "count": 1
            }
          ]
        },
        {
          "id": "SOR-91",
          "count": 1,
          "printings": [
            {
              "key": "SOR-91",
              "variant": "Standard Foil",
              "count": 1
            }
          ]
        },
        {
          "id": "SOR-222",
          "count": 3,
          "printings": [
            {
              "key": "SOR-222",
              "variant": "Standard",
              "count": 3
            }
          ]
        },
        {
          "id": "SOR-92",
          "count": 1,
          "printings": [
            {
              "key": "SOR-92",
              "variant": "Standard",
              "count": 1
            }
          ]
        },
        {
          "id": "SOR-187",
          "count": 1,
          "printings": [
            {
              "key": "SOR-187",
              "variant": "Standard",
              "count": 1
            }
          ]
        },
        {
          "id": "SOR-176",
          "count": 3,
          "printings": [
            {
              "key": "SOR-176",
              "variant": "Standard",
              "count": 3
            }
          ]
        },
        {
          "id": "SOR-207",
          "count": 2,
          "printings": [
            {
              "key": "SOR-207",
              "variant": "Standard",
              "count": 2
            }
          ]
        },
        {
          "id": "SOR-227",
          "count": 2,
          "printings": [
            {
              "key": "SOR-227",
              "variant": "Standard",
              "count": 2
            }
          ]
        },
        {
          "id": "SOR-228",
          "count": 3,
          "printings": [
            {
              "key": "SOR-228",
              "variant": "Standard",
              "count": 3
            }
          ]
        },
        {
          "id": "SOR-179",
          "count": 1,
          "printings": [
            {
              "key": "SOR-179",
              "variant": "Standard Foil",
              "count": 1
            }
          ]
        },
        {
          "id": "SOR-229",
          "count": 3,
          "printings": [
            {
              "key": "SOR-229",
              "variant": "Standard",
              "count": 3
            }
          ]
        },
        {
          "id": "SOR-112",
          "count": 3,
          "printings": [
            {
              "key": "SOR-112",
              "variant": "Standard",
              "count": 3
            }
          ]
        },
        {
          "id": "SOR-180",
          "count": 2,
          "printings": [
            {
              "key": "SOR-180",
              "variant": "Standard",
              "count": 2
            }
          ]
        },
        {
          "id": "SOR-83",
          "count": 3,
          "printings": [
            {
              "key": "SOR-83",
              "variant": "Standard",
              "count": 3
            }
          ]
        },
        {
          "id": "SOR-211",
          "count": 3,
          "printings": [
            {
              "key": "SOR-211",
              "variant": "Standard",
              "count": 3
            }
          ]
        },
        {
          "id": "SOR-231",
          "count": 3,
          "printings": [
            {
              "key": "SOR-231",
              "variant": "Standard",
              "count": 3
            }
          ]
        },
        {
          "id": "SOR-115",
          "count": 2,
          "printings": [
            {
              "key": "SOR-379",
              "variant": "Hyperspace Foil",
              "count": 1
            },
            {
              "key": "SOR-115",
              "variant": "Standard",
              "count": 1
            }
          ]
        },
        {
          "id": "SOR-182",
          "count": 1,
          "printings": [
            {
              "key": "SOR-182",
              "variant": "Standard",
              "count": 1
            }
          ]
        },
        {
          "id": "SOR-183",
          "count": 3,
          "printings": [
            {
              "key": "SOR-183",
              "variant": "Standard",
              "count": 3
            }
          ]
        },
        {
          "id": "SOR-86",
          "count": 3,
          "printings": [
            {
              "key": "SOR-86",
              "variant": "Standard Foil",
              "count": 1
            },
            {
              "key": "SOR-86",
              "variant": "Standard",
              "count": 2
            }
          ]
        },
        {
          "id": "SOR-87",
          "count": 1,
          "printings": [
            {
              "key": "SOR-87",
              "variant": "Standard",
              "count": 1
            }
          ]
        },
        {
          "id": "SOR-89",
          "count": 1,
          "printings": [
            {
              "key": "SOR-89",
              "variant": "Standard",
              "count": 1
            }
          ]
        }
      ]
    },
    {
      "id": "travel-two-fronts-one-rebellion",
      "name": "Two Fronts, One Rebellion",
      "archetype": "Aggro · Go-wide Rebels",
      "identity": "This deck wins by keeping two ready Rebels at all times and compressing two attacks into one Leia action, creating a damage-and-initiative advantage no defensive line can schedule around.",
      "aspects": [
        "Command",
        "Heroism",
        "Aggression"
      ],
      "leader": {
        "id": "SOR-9",
        "printing": "SOR-9",
        "variant": "Standard"
      },
      "base": {
        "id": "SOR-26",
        "printing": "SOR-26",
        "variant": "Standard"
      },
      "cards": [
        {
          "id": "SOR-245",
          "count": 2,
          "printings": [
            {
              "key": "SOR-245",
              "variant": "Standard Foil",
              "count": 1
            },
            {
              "key": "SOR-245",
              "variant": "Standard",
              "count": 1
            }
          ]
        },
        {
          "id": "SOR-103",
          "count": 1,
          "printings": [
            {
              "key": "SOR-103",
              "variant": "Standard",
              "count": 1
            }
          ]
        },
        {
          "id": "SOR-93",
          "count": 2,
          "printings": [
            {
              "key": "SOR-93",
              "variant": "Standard",
              "count": 2
            }
          ]
        },
        {
          "id": "SOR-94",
          "count": 1,
          "printings": [
            {
              "key": "SOR-94",
              "variant": "Standard Foil",
              "count": 1
            }
          ]
        },
        {
          "id": "SOR-157",
          "count": 3,
          "printings": [
            {
              "key": "SOR-157",
              "variant": "Standard",
              "count": 3
            }
          ]
        },
        {
          "id": "ASH-259",
          "count": 1,
          "printings": [
            {
              "key": "ASH-761",
              "variant": "Hyperspace Foil",
              "count": 1
            }
          ]
        },
        {
          "id": "SOR-236",
          "count": 3,
          "printings": [
            {
              "key": "SOR-236",
              "variant": "Standard",
              "count": 3
            }
          ]
        },
        {
          "id": "SOR-140",
          "count": 1,
          "printings": [
            {
              "key": "SOR-140",
              "variant": "Standard",
              "count": 1
            }
          ]
        },
        {
          "id": "SOR-108",
          "count": 1,
          "printings": [
            {
              "key": "SOR-108",
              "variant": "Standard",
              "count": 1
            }
          ]
        },
        {
          "id": "SOR-237",
          "count": 3,
          "printings": [
            {
              "key": "SOR-237",
              "variant": "Standard",
              "count": 3
            }
          ]
        },
        {
          "id": "SOR-95",
          "count": 2,
          "printings": [
            {
              "key": "SOR-95",
              "variant": "Standard",
              "count": 2
            }
          ]
        },
        {
          "id": "SOR-238",
          "count": 2,
          "printings": [
            {
              "key": "SOR-238",
              "variant": "Standard",
              "count": 2
            }
          ]
        },
        {
          "id": "ASH-249",
          "count": 1,
          "printings": [
            {
              "key": "ASH-249",
              "variant": "Standard",
              "count": 1
            }
          ]
        },
        {
          "id": "SOR-141",
          "count": 2,
          "printings": [
            {
              "key": "SOR-141",
              "variant": "Standard",
              "count": 2
            }
          ]
        },
        {
          "id": "ASH-250",
          "count": 1,
          "printings": [
            {
              "key": "ASH-250",
              "variant": "Standard",
              "count": 1
            }
          ]
        },
        {
          "id": "SOR-239",
          "count": 2,
          "printings": [
            {
              "key": "SOR-239",
              "variant": "Standard",
              "count": 2
            }
          ]
        },
        {
          "id": "ASH-120",
          "count": 1,
          "printings": [
            {
              "key": "ASH-120",
              "variant": "Standard",
              "count": 1
            }
          ]
        },
        {
          "id": "ASH-169",
          "count": 1,
          "printings": [
            {
              "key": "ASH-169",
              "variant": "Standard",
              "count": 1
            }
          ]
        },
        {
          "id": "ASH-107",
          "count": 1,
          "printings": [
            {
              "key": "ASH-107",
              "variant": "Standard",
              "count": 1
            }
          ]
        },
        {
          "id": "ASH-122",
          "count": 1,
          "printings": [
            {
              "key": "ASH-122",
              "variant": "Standard",
              "count": 1
            }
          ]
        },
        {
          "id": "SOR-98",
          "count": 1,
          "printings": [
            {
              "key": "SOR-98",
              "variant": "Standard",
              "count": 1
            }
          ]
        },
        {
          "id": "SOR-143",
          "count": 1,
          "printings": [
            {
              "key": "SOR-143",
              "variant": "Standard",
              "count": 1
            }
          ]
        },
        {
          "id": "SOR-240",
          "count": 3,
          "printings": [
            {
              "key": "SOR-240",
              "variant": "Standard",
              "count": 3
            }
          ]
        },
        {
          "id": "SOR-113",
          "count": 1,
          "printings": [
            {
              "key": "SOR-113",
              "variant": "Standard",
              "count": 1
            }
          ]
        },
        {
          "id": "SOR-241",
          "count": 1,
          "printings": [
            {
              "key": "SOR-241",
              "variant": "Standard",
              "count": 1
            }
          ]
        },
        {
          "id": "SOR-242",
          "count": 1,
          "printings": [
            {
              "key": "SOR-242",
              "variant": "Standard",
              "count": 1
            }
          ]
        },
        {
          "id": "SOR-243",
          "count": 1,
          "printings": [
            {
              "key": "SOR-243",
              "variant": "Standard",
              "count": 1
            }
          ]
        },
        {
          "id": "ASH-126",
          "count": 1,
          "printings": [
            {
              "key": "ASH-628",
              "variant": "Hyperspace Foil",
              "count": 1
            }
          ]
        },
        {
          "id": "SOR-164",
          "count": 1,
          "printings": [
            {
              "key": "SOR-164",
              "variant": "Standard",
              "count": 1
            }
          ]
        },
        {
          "id": "ASH-130",
          "count": 1,
          "printings": [
            {
              "key": "ASH-130",
              "variant": "Standard",
              "count": 1
            }
          ]
        },
        {
          "id": "SOR-244",
          "count": 2,
          "printings": [
            {
              "key": "SOR-244",
              "variant": "Standard Foil",
              "count": 1
            },
            {
              "key": "SOR-244",
              "variant": "Standard",
              "count": 1
            }
          ]
        },
        {
          "id": "SOR-100",
          "count": 1,
          "printings": [
            {
              "key": "SOR-100",
              "variant": "Standard",
              "count": 1
            }
          ]
        },
        {
          "id": "SOR-146",
          "count": 1,
          "printings": [
            {
              "key": "SOR-146",
              "variant": "Standard",
              "count": 1
            }
          ]
        },
        {
          "id": "SOR-148",
          "count": 1,
          "printings": [
            {
              "key": "SOR-148",
              "variant": "Standard",
              "count": 1
            }
          ]
        },
        {
          "id": "SOR-102",
          "count": 1,
          "printings": [
            {
              "key": "SOR-102",
              "variant": "Standard",
              "count": 1
            }
          ]
        }
      ]
    },
    {
      "id": "travel-dead-mans-sightline",
      "name": "Dead Man's Sightline",
      "archetype": "Control · Ping attrition",
      "identity": "Cad's repeatable one-damage ping finishes wounded units and changes every combat calculation; Vigilance supplies the durable control shell.",
      "aspects": [
        "Aggression",
        "Villainy",
        "Vigilance"
      ],
      "leader": {
        "id": "ASH-11",
        "printing": "ASH-11",
        "variant": "Standard"
      },
      "base": {
        "id": "ASH-20",
        "printing": "ASH-20",
        "variant": "Standard"
      },
      "cards": [
        {
          "id": "SOR-139",
          "count": 3,
          "printings": [
            {
              "key": "SOR-139",
              "variant": "Standard",
              "count": 3
            }
          ]
        },
        {
          "id": "ASH-186",
          "count": 1,
          "printings": [
            {
              "key": "ASH-450",
              "variant": "Hyperspace",
              "count": 1
            }
          ]
        },
        {
          "id": "SOR-76",
          "count": 2,
          "printings": [
            {
              "key": "SOR-341",
              "variant": "Hyperspace",
              "count": 1
            },
            {
              "key": "SOR-76",
              "variant": "Standard Foil",
              "count": 1
            }
          ]
        },
        {
          "id": "SOR-172",
          "count": 3,
          "printings": [
            {
              "key": "SOR-172",
              "variant": "Standard Foil",
              "count": 1
            },
            {
              "key": "SOR-172",
              "variant": "Standard",
              "count": 2
            }
          ]
        },
        {
          "id": "ASH-188",
          "count": 1,
          "printings": [
            {
              "key": "ASH-452",
              "variant": "Hyperspace",
              "count": 1
            }
          ]
        },
        {
          "id": "SOR-77",
          "count": 1,
          "printings": [
            {
              "key": "SOR-77",
              "variant": "Standard Foil",
              "count": 1
            }
          ]
        },
        {
          "id": "SOR-78",
          "count": 2,
          "printings": [
            {
              "key": "SOR-78",
              "variant": "Standard",
              "count": 2
            }
          ]
        },
        {
          "id": "ASH-151",
          "count": 1,
          "printings": [
            {
              "key": "ASH-151",
              "variant": "Standard",
              "count": 1
            }
          ]
        },
        {
          "id": "SOR-128",
          "count": 3,
          "printings": [
            {
              "key": "SOR-128",
              "variant": "Standard",
              "count": 3
            }
          ]
        },
        {
          "id": "ASH-45",
          "count": 2,
          "printings": [
            {
              "key": "ASH-45",
              "variant": "Standard",
              "count": 2
            }
          ]
        },
        {
          "id": "ASH-141",
          "count": 1,
          "printings": [
            {
              "key": "ASH-643",
              "variant": "Hyperspace Foil",
              "count": 1
            }
          ]
        },
        {
          "id": "SOR-130",
          "count": 3,
          "printings": [
            {
              "key": "SOR-130",
              "variant": "Standard",
              "count": 3
            }
          ]
        },
        {
          "id": "SOR-32",
          "count": 3,
          "printings": [
            {
              "key": "SOR-32",
              "variant": "Standard Foil",
              "count": 1
            },
            {
              "key": "SOR-32",
              "variant": "Standard",
              "count": 2
            }
          ]
        },
        {
          "id": "ASH-143",
          "count": 1,
          "printings": [
            {
              "key": "ASH-407",
              "variant": "Hyperspace",
              "count": 1
            }
          ]
        },
        {
          "id": "SOR-33",
          "count": 3,
          "printings": [
            {
              "key": "SOR-33",
              "variant": "Standard",
              "count": 3
            }
          ]
        },
        {
          "id": "ASH-170",
          "count": 2,
          "printings": [
            {
              "key": "ASH-170",
              "variant": "Standard",
              "count": 2
            }
          ]
        },
        {
          "id": "SOR-131",
          "count": 1,
          "printings": [
            {
              "key": "SOR-131",
              "variant": "Standard",
              "count": 1
            }
          ]
        },
        {
          "id": "ASH-30",
          "count": 1,
          "printings": [
            {
              "key": "ASH-30",
              "variant": "Standard",
              "count": 1
            }
          ]
        },
        {
          "id": "ASH-242",
          "count": 1,
          "printings": [
            {
              "key": "ASH-242",
              "variant": "Standard",
              "count": 1
            }
          ]
        },
        {
          "id": "ASH-48",
          "count": 1,
          "printings": [
            {
              "key": "ASH-48",
              "variant": "Standard",
              "count": 1
            }
          ]
        },
        {
          "id": "SOR-132",
          "count": 3,
          "printings": [
            {
              "key": "SOR-396",
              "variant": "Hyperspace",
              "count": 1
            },
            {
              "key": "SOR-132",
              "variant": "Standard",
              "count": 2
            }
          ]
        },
        {
          "id": "ASH-145",
          "count": 2,
          "printings": [
            {
              "key": "ASH-145",
              "variant": "Standard",
              "count": 2
            }
          ]
        },
        {
          "id": "ASH-146",
          "count": 1,
          "printings": [
            {
              "key": "ASH-146",
              "variant": "Standard",
              "count": 1
            }
          ]
        },
        {
          "id": "ASH-244",
          "count": 2,
          "printings": [
            {
              "key": "ASH-746",
              "variant": "Hyperspace Foil",
              "count": 1
            },
            {
              "key": "ASH-244",
              "variant": "Standard",
              "count": 1
            }
          ]
        },
        {
          "id": "SOR-133",
          "count": 2,
          "printings": [
            {
              "key": "SOR-133",
              "variant": "Standard",
              "count": 2
            }
          ]
        },
        {
          "id": "ASH-176",
          "count": 2,
          "printings": [
            {
              "key": "ASH-176",
              "variant": "Standard",
              "count": 2
            }
          ]
        },
        {
          "id": "ASH-147",
          "count": 1,
          "printings": [
            {
              "key": "ASH-147",
              "variant": "Standard",
              "count": 1
            }
          ]
        },
        {
          "id": "SOR-135",
          "count": 1,
          "printings": [
            {
              "key": "SOR-399",
              "variant": "Hyperspace",
              "count": 1
            }
          ]
        }
      ]
    },
    {
      "id": "travel-twin-suns-resurgence",
      "name": "Twin Suns Resurgence",
      "archetype": "Midrange · Healing value",
      "identity": "Luke converts every attack into durability, letting efficient Heroism units win repeated combats before capital ships finish the game.",
      "aspects": [
        "Vigilance",
        "Heroism",
        "Command"
      ],
      "leader": {
        "id": "ASH-5",
        "printing": "ASH-269",
        "variant": "Hyperspace"
      },
      "base": {
        "id": "ASH-22",
        "printing": "ASH-22",
        "variant": "Standard"
      },
      "cards": [
        {
          "id": "ASH-89",
          "count": 2,
          "printings": [
            {
              "key": "ASH-89",
              "variant": "Standard",
              "count": 2
            }
          ]
        },
        {
          "id": "ASH-92",
          "count": 2,
          "printings": [
            {
              "key": "ASH-356",
              "variant": "Hyperspace",
              "count": 1
            },
            {
              "key": "ASH-92",
              "variant": "Standard",
              "count": 1
            }
          ]
        },
        {
          "id": "ASH-258",
          "count": 2,
          "printings": [
            {
              "key": "ASH-258",
              "variant": "Standard",
              "count": 2
            }
          ]
        },
        {
          "id": "SOR-77",
          "count": 1,
          "printings": [
            {
              "key": "SOR-77",
              "variant": "Standard",
              "count": 1
            }
          ]
        },
        {
          "id": "SOR-78",
          "count": 1,
          "printings": [
            {
              "key": "SOR-78",
              "variant": "Standard",
              "count": 1
            }
          ]
        },
        {
          "id": "SOR-59",
          "count": 3,
          "printings": [
            {
              "key": "SOR-59",
              "variant": "Standard",
              "count": 3
            }
          ]
        },
        {
          "id": "ASH-68",
          "count": 1,
          "printings": [
            {
              "key": "ASH-68",
              "variant": "Standard",
              "count": 1
            }
          ]
        },
        {
          "id": "ASH-117",
          "count": 1,
          "printings": [
            {
              "key": "ASH-117",
              "variant": "Standard",
              "count": 1
            }
          ]
        },
        {
          "id": "SOR-237",
          "count": 1,
          "printings": [
            {
              "key": "SOR-237",
              "variant": "Standard",
              "count": 1
            }
          ]
        },
        {
          "id": "ASH-70",
          "count": 1,
          "printings": [
            {
              "key": "ASH-70",
              "variant": "Standard",
              "count": 1
            }
          ]
        },
        {
          "id": "ASH-71",
          "count": 1,
          "printings": [
            {
              "key": "ASH-71",
              "variant": "Standard",
              "count": 1
            }
          ]
        },
        {
          "id": "ASH-105",
          "count": 1,
          "printings": [
            {
              "key": "ASH-105",
              "variant": "Standard",
              "count": 1
            }
          ]
        },
        {
          "id": "SOR-238",
          "count": 1,
          "printings": [
            {
              "key": "SOR-238",
              "variant": "Standard",
              "count": 1
            }
          ]
        },
        {
          "id": "SOR-109",
          "count": 1,
          "printings": [
            {
              "key": "SOR-109",
              "variant": "Standard",
              "count": 1
            }
          ]
        },
        {
          "id": "ASH-106",
          "count": 1,
          "printings": [
            {
              "key": "ASH-106",
              "variant": "Standard",
              "count": 1
            }
          ]
        },
        {
          "id": "SOR-62",
          "count": 1,
          "printings": [
            {
              "key": "SOR-62",
              "variant": "Standard",
              "count": 1
            }
          ]
        },
        {
          "id": "SOR-44",
          "count": 3,
          "printings": [
            {
              "key": "SOR-44",
              "variant": "Standard Foil",
              "count": 1
            },
            {
              "key": "SOR-44",
              "variant": "Standard",
              "count": 2
            }
          ]
        },
        {
          "id": "ASH-251",
          "count": 2,
          "printings": [
            {
              "key": "ASH-251",
              "variant": "Standard",
              "count": 2
            }
          ]
        },
        {
          "id": "SOR-63",
          "count": 2,
          "printings": [
            {
              "key": "SOR-63",
              "variant": "Standard",
              "count": 2
            }
          ]
        },
        {
          "id": "ASH-252",
          "count": 2,
          "printings": [
            {
              "key": "ASH-516",
              "variant": "Hyperspace",
              "count": 2
            }
          ]
        },
        {
          "id": "ASH-75",
          "count": 1,
          "printings": [
            {
              "key": "ASH-75",
              "variant": "Standard",
              "count": 1
            }
          ]
        },
        {
          "id": "SOR-45",
          "count": 2,
          "printings": [
            {
              "key": "SOR-45",
              "variant": "Standard",
              "count": 2
            }
          ]
        },
        {
          "id": "ASH-78",
          "count": 2,
          "printings": [
            {
              "key": "ASH-580",
              "variant": "Hyperspace Foil",
              "count": 1
            },
            {
              "key": "ASH-78",
              "variant": "Standard",
              "count": 1
            }
          ]
        },
        {
          "id": "SOR-46",
          "count": 2,
          "printings": [
            {
              "key": "SOR-46",
              "variant": "Standard",
              "count": 2
            }
          ]
        },
        {
          "id": "ASH-127",
          "count": 1,
          "printings": [
            {
              "key": "ASH-127",
              "variant": "Standard",
              "count": 1
            }
          ]
        },
        {
          "id": "SOR-49",
          "count": 2,
          "printings": [
            {
              "key": "SOR-315",
              "variant": "Hyperspace",
              "count": 1
            },
            {
              "key": "SOR-49",
              "variant": "Standard",
              "count": 1
            }
          ]
        },
        {
          "id": "ASH-64",
          "count": 2,
          "printings": [
            {
              "key": "ASH-64",
              "variant": "Standard",
              "count": 2
            }
          ]
        },
        {
          "id": "ASH-65",
          "count": 1,
          "printings": [
            {
              "key": "ASH-65",
              "variant": "Standard",
              "count": 1
            }
          ]
        },
        {
          "id": "ASH-133",
          "count": 1,
          "printings": [
            {
              "key": "ASH-133",
              "variant": "Standard",
              "count": 1
            }
          ]
        },
        {
          "id": "SOR-53",
          "count": 2,
          "printings": [
            {
              "key": "SOR-53",
              "variant": "Standard",
              "count": 2
            }
          ]
        },
        {
          "id": "ASH-114",
          "count": 2,
          "printings": [
            {
              "key": "ASH-378",
              "variant": "Hyperspace",
              "count": 1
            },
            {
              "key": "ASH-114",
              "variant": "Standard",
              "count": 1
            }
          ]
        },
        {
          "id": "SOR-54",
          "count": 1,
          "printings": [
            {
              "key": "SOR-54",
              "variant": "Standard",
              "count": 1
            }
          ]
        },
        {
          "id": "ASH-134",
          "count": 1,
          "printings": [
            {
              "key": "ASH-134",
              "variant": "Standard",
              "count": 1
            }
          ]
        }
      ]
    }
  ]
}
